convert_dataset/__init__.py
convert_dataset/prompt_generator.py
convert_dataset-0.1.0.dist-info/METADATA
convert_dataset-0.1.0.dist-info/WHEEL
convert_dataset-0.1.0.dist-info/entry_points.txt
convert_dataset-0.1.0.dist-info/top_level.txt
convert_dataset-0.1.0.dist-info/RECORD
