Metadata-Version: 2.1
Name: convert-dataset
Version: 0.1.0
Summary: Tool to generate LLM prompt to easily convert dataset to a specific format
Requires-Python: >=3.9.18
Requires-Dist: describe-dataset>=0.1.2
